apek/__init__.py
apek/_base.py
apek/_text.py
apek/helps.py
apek/largeNumber.py
apek/meta.py
apek/typing.py
apek-0.0.4.post1.dist-info/LICENSE
apek-0.0.4.post1.dist-info/METADATA
apek-0.0.4.post1.dist-info/WHEEL
apek-0.0.4.post1.dist-info/RECORD
