Metadata-Version: 2.3
Name: apek
Version: 0.0.4.post1
Summary: 
Author: apeking1819
Requires-Python: >=3.8
Classifier: Programming Language :: Python :: 3
Classifier: Programming Language :: Python :: 3.8
Classifier: Programming Language :: Python :: 3.9
Classifier: Programming Language :: Python :: 3.10
Classifier: Programming Language :: Python :: 3.11
Classifier: Programming Language :: Python :: 3.12
Classifier: Programming Language :: Python :: 3.13
Requires-Dist: colorama (>=0.4.4,<0.5.0)
Requires-Dist: mpmath (>=1.3.0,<1.4.0)
